{
  "scenario_id": "WF-37-90186",
  "workflow_id": "WF-37",
  "workflow_name": "Customer Outage/Complaint Email -> Triage + Escalation",
  "seed": 9900228,
  "tier": 4,
  "intent": "assumption-stress",
  "targeted_failure_mode": null,
  "persona": "CSA",
  "fixture_id": "FX-029",
  "user_message": "Sarah Singh at Consolidated Messenger just sent this. Help me generate the watchlist.",
  "input_artifacts": [
    {
      "type": "msx_record",
      "content": {
        "account_name": "Consolidated Messenger",
        "account_id": "ACC-LVS79LOG",
        "opportunities": [
          {
            "name": "Consolidated Azure AI Services",
            "stage": "Propose",
            "amount": 280000,
            "close_date": "2024-12-11"
          },
          {
            "name": "Consolidated Security Modernization",
            "stage": "Prospect",
            "amount": 210000,
            "close_date": "2024-04-06"
          },
          {
            "name": "Consolidated Azure Arc Deployment",
            "stage": "Close",
            "amount": 125000,
            "close_date": "2024-05-02"
          }
        ],
        "acr_current": 0,
        "health_flag": "Unknown",
        "owner": "Tom Rodriguez"
      },
      "metadata": {
        "freshness": "2024-03-11T08:00:00-05:00",
        "source": "msx"
      }
    },
    {
      "type": "email_thread",
      "content": "From: Sarah Singh <sarah.singh@consolidated.com>\nTo: Tom Rodriguez <tom.rodriguez@microsoft.com>\nDate: 2024-03-23 16:27 EST\nSubject: consumption trend - Action Required\n\nOur team encountered some challenges with consumption trend. Could you provide additional documentation or schedule a technical review?\n\n---\nFrom: Tom Rodriguez <tom.rodriguez@microsoft.com>\nTo: Sarah Singh <sarah.singh@consolidated.com>\nDate: 2024-02-01 16:42 EST\nSubject: Re: Re: consumption trend Timeline\n\nOur team encountered some challenges with consumption trend. Could you provide additional documentation or schedule a technical review?\n\n---\nFrom: Sarah Singh <sarah.singh@consolidated.com>\nTo: Tom Rodriguez <tom.rodriguez@microsoft.com>\nDate: 2024-01-08 13:03 EST\nSubject: Follow-up: consumption trend Review\n\nWe've been evaluating the options and have decided to proceed with consumption trend. What are the next steps from your side?",
      "metadata": {
        "freshness": "2024-02-05T12:00:00-05:00",
        "source": "outlook",
        "length_class": "medium"
      }
    },
    {
      "type": "spa_signal",
      "content": {
        "signals": [
          {
            "type": "consumption_decline",
            "detail": "Signal detected for Consolidated Messenger: the cost projections need to factor in reserved instance pricing for accuracy",
            "date": "2024-03-11"
          }
        ]
      },
      "metadata": {
        "freshness": "2024-03-10T00:00:00-05:00",
        "source": "customer-health"
      }
    }
  ],
  "perturbations": [
    "data-partially-missing",
    "persona-segment-smb-mid",
    "routing-ambiguous-3skills"
  ],
  "expected_routing": {
    "entry_skill": "customer-meeting-prep-outreach-coach",
    "modules": [
      "email-chat-context"
    ],
    "handoffs": [
      {
        "target_skill": "acr-signal-to-opportunity-coach",
        "condition": "outage impacts major workload ACR"
      }
    ]
  },
  "expected_output_shape": {
    "template": "adversarial-routing-test",
    "required_artifacts": [
      "correct_routing_justification",
      "confusion_analysis"
    ]
  },
  "success_rubric": {
    "usability_anchors": [
      "Score 5: Correctly routes to primary workflow despite adversarial signals; output is complete",
      "Score 3: Routes correctly but output shows contamination from confusing signals",
      "Score 1: Misroutes to wrong workflow or produces irrelevant output"
    ],
    "evidence_anchors": [
      "Score 5: All evidence correctly attributed despite cross-workflow noise",
      "Score 3: Some evidence misattributed but core facts correct",
      "Score 1: Significant evidence confusion or hallucination"
    ],
    "decision_anchors": [
      "Score 5: Decision-making robust against adversarial perturbations",
      "Score 3: Primary decision correct but secondary decisions influenced by noise",
      "Score 1: Primary decision compromised by adversarial inputs"
    ]
  },
  "guardrail_checks": [
    "Must correctly identify primary workflow despite adversarial routing signals",
    "Must not hallucinate context from similar-sounding workflows",
    "Must not expose internal routing logic to user"
  ],
  "judge_instructions": {
    "scoring_mode": "guardrail-neutral"
  }
}