{
  "scenario_id": "WF-11-90408",
  "workflow_id": "WF-11",
  "workflow_name": "Pre-Meeting Brief",
  "seed": 9900450,
  "tier": 2,
  "intent": "adherence",
  "targeted_failure_mode": null,
  "persona": "DSSP",
  "fixture_id": "FX-001",
  "user_message": "Help me build whitespace analysis for Contoso Ltd. We had a deep-dive last month -- need the follow-up.",
  "input_artifacts": [
    {
      "type": "msx_record",
      "content": {
        "account_name": "Contoso Ltd",
        "account_id": "ACC-VWW2DK8X",
        "opportunities": [
          {
            "name": "Contoso Power Platform",
            "stage": "Propose",
            "amount": 560000,
            "close_date": "2024-12-28"
          }
        ],
        "acr_current": 78949.7,
        "health_flag": "Healthy",
        "owner": "Marcus Williams"
      },
      "metadata": {
        "freshness": "2024-03-11T08:00:00-05:00",
        "source": "msx"
      }
    },
    {
      "type": "email_thread",
      "content": "From: Angela Doyle <angela.doyle@contosoltd.com>\nTo: Marcus Williams <marcus.williams@microsoft.com>\nDate: 2024-03-07 15:37 EST\nSubject: Follow-up: whitespace analysis Review\n\nJust checking in on the whitespace analysis proposal. Our Director of IT is asking for a status update before the board meeting next week.\n\n---\nFrom: Marcus Williams <marcus.williams@microsoft.com>\nTo: Angela Doyle <angela.doyle@contosoltd.com>\nDate: 2024-02-03 10:57 EST\nSubject: Re: Re: whitespace analysis Timeline\n\nThank you for the discussion last week. We'd like to move forward with whitespace analysis. Can we schedule a call this week to finalize the timeline?",
      "metadata": {
        "freshness": "2024-03-04T14:00:00-05:00",
        "source": "outlook",
        "length_class": "short"
      }
    },
    {
      "type": "transcript",
      "content": "Meeting: whitespace analysis Discussion - Contoso Ltd\nDate: 2024-01-22\nDuration: 45 minutes\nAttendees: Angela Doyle (Contoso Ltd), Marcus Williams (Microsoft)\n\n[00:01:15] Angela Doyle (Contoso Ltd): Appreciate everyone making time. The main agenda today is whitespace analysis.\n\n[00:06:00] Angela Doyle (Contoso Ltd): Let me add some context -- we've been working on vendor dependencies and found that the existing infrastructure won't support the target workload without upgrades.\n\n[00:08:00] Angela Doyle (Contoso Ltd): Our VP reviewed this and has concerns about resource allocation. Can we address those?\n\n[00:13:00] Angela Doyle (Contoso Ltd): Our CTO reviewed this and has concerns about stakeholder alignment. Can we address those?\n\n[00:18:00] Angela Doyle (Contoso Ltd): Let me add some context -- we've been working on partner engagement and found that there's a dependency on the security team's review that could delay us.\n\n[00:22:00] Angela Doyle (Contoso Ltd): The timeline for integration complexity is aggressive. We need to validate the assumptions.\n\n[00:24:00] Angela Doyle (Contoso Ltd): Our CTO reviewed this and has concerns about resource allocation. Can we address those?",
      "metadata": {
        "freshness": "2024-01-02T00:00:00-05:00",
        "source": "teams-transcript",
        "speaker_attribution": "named",
        "length_class": "medium"
      }
    },
    {
      "type": "calendar_event",
      "content": {
        "title": "Contoso Ltd - whitespace analysis",
        "start": "2024-03-12T11:00:00-05:00",
        "end": "2024-03-15T11:00:00-05:00",
        "attendees": [
          {
            "name": "Marcus Williams",
            "email": "marcus.williams@microsoft.com"
          },
          {
            "name": "Angela Doyle",
            "email": "angela.doyle@example.com"
          }
        ]
      },
      "metadata": {
        "freshness": "2024-03-11T06:00:00-05:00",
        "source": "outlook-calendar"
      }
    }
  ],
  "perturbations": [
    "persona-geo-na",
    "persona-tenure-mid",
    "routing-ambiguous-3skills"
  ],
  "expected_routing": {
    "entry_skill": "customer-meeting-prep-outreach-coach",
    "modules": [
      "meeting-prep",
      "contact-stakeholder-map"
    ]
  },
  "expected_output_shape": {
    "template": "adversarial-routing-test",
    "required_artifacts": [
      "correct_routing_justification",
      "confusion_analysis"
    ]
  },
  "success_rubric": {
    "usability_anchors": [
      "Score 5: Correctly routes to primary workflow despite adversarial signals; output is complete",
      "Score 3: Routes correctly but output shows contamination from confusing signals",
      "Score 1: Misroutes to wrong workflow or produces irrelevant output"
    ],
    "evidence_anchors": [
      "Score 5: All evidence correctly attributed despite cross-workflow noise",
      "Score 3: Some evidence misattributed but core facts correct",
      "Score 1: Significant evidence confusion or hallucination"
    ],
    "decision_anchors": [
      "Score 5: Decision-making robust against adversarial perturbations",
      "Score 3: Primary decision correct but secondary decisions influenced by noise",
      "Score 1: Primary decision compromised by adversarial inputs"
    ]
  },
  "guardrail_checks": [
    "Must correctly identify primary workflow despite adversarial routing signals",
    "Must not hallucinate context from similar-sounding workflows",
    "Must not expose internal routing logic to user"
  ],
  "judge_instructions": {
    "scoring_mode": "standard"
  }
}