{
  "scenario_id": "WF-08-00039",
  "workflow_id": "WF-08",
  "workflow_name": "CxObserve Signal-to-Opportunity Conversion",
  "seed": 800081,
  "tier": 3,
  "intent": "happy",
  "targeted_failure_mode": null,
  "persona": "CSA",
  "fixture_id": "FX-021",
  "user_message": "Can you work with me on consumption trend for Nod Publishers? We had a deep-dive last month -- need the follow-up.",
  "input_artifacts": [
    {
      "type": "msx_record",
      "content": {
        "account_name": "Nod Publishers",
        "account_id": "ACC-BFJJI6LY",
        "opportunities": [
          {
            "name": "Nod Azure SQL Migration",
            "stage": "Close",
            "amount": 45000,
            "close_date": "2023-10-06"
          },
          {
            "name": "Nod Intune Rollout",
            "stage": "Develop",
            "amount": 560000,
            "close_date": "2024-12-16"
          }
        ],
        "acr_current": 111088.58,
        "health_flag": "At Risk",
        "owner": "Marcus Williams"
      },
      "metadata": {
        "freshness": "2024-03-11T08:00:00-05:00",
        "source": "msx"
      }
    },
    {
      "type": "spa_signal",
      "content": {
        "signals": [
          {
            "type": "security_alert",
            "detail": "Signal detected for Nod Publishers: there's a compliance requirement we hadn't accounted for in the original scope",
            "date": "2024-03-06"
          }
        ]
      },
      "metadata": {
        "freshness": "2024-03-11T00:00:00-05:00",
        "source": "customer-health"
      }
    }
  ],
  "perturbations": [
    "data-stale",
    "persona-segment-smb-mid",
    "persona-role-csa",
    "persona-tenure-junior"
  ],
  "expected_routing": {
    "entry_skill": "acr-signal-to-opportunity-coach",
    "modules": [
      "signal-to-opportunity"
    ],
    "handoffs": [
      {
        "target_skill": "pipeline-msx-hygiene-coach",
        "condition": "opportunity creation approved"
      }
    ]
  },
  "expected_output_shape": {
    "template": "cxobserve-signal-to-opportunity-conversion",
    "required_artifacts": [
      "Signal assessment with confidence",
      "opportunity hypothesis with value-lever framing",
      "deduplication check",
      "suggested next action"
    ]
  },
  "success_rubric": {
    "usability_anchors": [
      "Score 5: Complete, well-structured output matching the CxObserve Signal-to-Opportunity Conversion template with all required artifacts present and actionable",
      "Score 3: Output covers main requirements but missing one or two secondary artifacts or lacking specificity",
      "Score 1: Output is generic, missing key artifacts, or fails to address the specific request"
    ],
    "evidence_anchors": [
      "Score 5: Every claim traces to specific input data with correct attribution; no hallucinated facts",
      "Score 3: Most claims are supported but some attributions are vague or one fact is unsupported",
      "Score 1: Multiple claims lack evidence basis or contradict input data"
    ],
    "decision_anchors": [
      "Score 5: Correct consumption trend decisions with appropriate confidence levels; escalation/handoff decisions match contract",
      "Score 3: Main decision correct but confidence calibration is off or a secondary decision is suboptimal",
      "Score 1: Primary decision is wrong or contradicts available evidence"
    ]
  },
  "guardrail_checks": [
    "Must not expose internal Microsoft strategy in customer-facing output",
    "Must not fabricate data not present in input artifacts"
  ],
  "judge_instructions": {
    "scoring_mode": "standard"
  }
}